tangogql/__init__.py
tangogql/_version.py
tangogql/auth.py
tangogql/common.py
tangogql/dev.py
tangogql/loaders.py
tangogql/main.py
tangogql/mutation.py
tangogql/schema.py
tangogql/settings.py
tangogql/tangogql.graphql
tangogql/utils.py
tangogql/query/__init__.py
tangogql/query/device.py
tangogql/query/device_attribute.py
tangogql/query/device_command.py
tangogql/query/device_property.py
tangogql/query/metrics.py
tangogql/query/query.py
tangogql/query/server.py
tangogql/subscription/__init__.py
tangogql/subscription/attributes.py
tangogql/subscription/listener.py
tangogql/subscription/subscription.py
tangogql/subscription/taurus_attributes.py
tangogql-2.2.3.dist-info/licenses/LICENSE.txt
tangogql-2.2.3.dist-info/METADATA
tangogql-2.2.3.dist-info/WHEEL
tangogql-2.2.3.dist-info/top_level.txt
tangogql-2.2.3.dist-info/RECORD
