Metadata-Version: 2.4
Name: tangogql
Version: 2.2.3
Summary: TangoGQL implementation using Ariadne
License:                     GNU GENERAL PUBLIC LICENSE
Project-URL: Repository, https://gitlab.com/tango-controls/web/tangogql-ariadne
Requires-Python: >=3.10
License-File: LICENSE.txt
Requires-Dist: pytango
Requires-Dist: ariadne
Requires-Dist: uvicorn
Requires-Dist: python-dateutil
Requires-Dist: aiocache
Requires-Dist: aiodataloader
Requires-Dist: pyjwt
Requires-Dist: pydantic-settings
Requires-Dist: websockets
Provides-Extra: tests
Requires-Dist: pytest; extra == "tests"
Requires-Dist: pytest-asyncio==0.26.0; extra == "tests"
Requires-Dist: pytest-cov; extra == "tests"
Requires-Dist: httpx; extra == "tests"
Requires-Dist: requests; extra == "tests"
Requires-Dist: pytango-db; extra == "tests"
Dynamic: license-file
